chevah_compat-0.45.2-nspkg.pth
chevah/compat/__init__.py
chevah/compat/administration.py
chevah/compat/avatar.py
chevah/compat/capabilities.py
chevah/compat/compat_users.py
chevah/compat/constants.py
chevah/compat/exceptions.py
chevah/compat/helpers.py
chevah/compat/interfaces.py
chevah/compat/nt_capabilities.py
chevah/compat/nt_filesystem.py
chevah/compat/nt_service.py
chevah/compat/nt_unicode_argv.py
chevah/compat/nt_users.py
chevah/compat/posix_filesystem.py
chevah/compat/unix_capabilities.py
chevah/compat/unix_filesystem.py
chevah/compat/unix_service.py
chevah/compat/unix_users.py
chevah/compat/winerrors.py
chevah/compat/testing/__init__.py
chevah/compat/testing/assertion.py
chevah/compat/testing/conditionals.py
chevah/compat/testing/constants.py
chevah/compat/testing/filesystem.py
chevah/compat/testing/mockup.py
chevah/compat/testing/nose_memory_usage.py
chevah/compat/testing/nose_run_reporter.py
chevah/compat/testing/nose_test_timer.py
chevah/compat/testing/testcase.py
chevah/compat/testing/threaded_reactor.py
chevah/compat/tests/__init__.py
chevah/compat/tests/domain/__init__.py
chevah/compat/tests/domain/test_filesystem.py
chevah/compat/tests/domain/test_system_users.py
chevah/compat/tests/elevated/__init__.py
chevah/compat/tests/elevated/test_capabilities.py
chevah/compat/tests/elevated/test_filesystem.py
chevah/compat/tests/elevated/test_system_users.py
chevah/compat/tests/elevated/testing/__init__.py
chevah/compat/tests/elevated/testing/test_filesystem.py
chevah/compat/tests/manual/__init__.py
chevah/compat/tests/manual/print_argv.py
chevah/compat/tests/mixin/__init__.py
chevah/compat/tests/mixin/filesystem.py
chevah/compat/tests/normal/__init__.py
chevah/compat/tests/normal/helper_sys_argv.py
chevah/compat/tests/normal/test_avatar.py
chevah/compat/tests/normal/test_capabilities.py
chevah/compat/tests/normal/test_filesystem.py
chevah/compat/tests/normal/test_nt_service.py
chevah_compat-0.45.2.dist-info/DESCRIPTION.rst
chevah_compat-0.45.2.dist-info/METADATA
chevah_compat-0.45.2.dist-info/RECORD
chevah_compat-0.45.2.dist-info/WHEEL
chevah_compat-0.45.2.dist-info/metadata.json
chevah_compat-0.45.2.dist-info/namespace_packages.txt
chevah_compat-0.45.2.dist-info/top_level.txt
