Metadata-Version: 2.0
Name: chevah-compat
Version: 0.45.2
Summary: Chevah OS Compatibility Layer.
Home-page: http://www.chevah.com
Author: Adi Roiban
Author-email: adi.roiban@chevah.com
License: BSD 3-Clause
Platform: any
Classifier: Development Status :: 4 - Beta
Classifier: Intended Audience :: Developers
Classifier: Programming Language :: Python
